[
  {
    "model": "JOURNEY",
    "total_vehicles": 3040,
    "keep": true
  },
  {
    "model": "CHALLENGER",
    "total_vehicles": 1267,
    "keep": true
  },
  {
    "model": "NITRO",
    "total_vehicles": 838,
    "keep": true
  },
  {
    "model": "CALIBER",
    "total_vehicles": 495,
    "keep": true
  },
  {
    "model": "CHARGER",
    "total_vehicles": 359,
    "keep": true
  },
  {
    "model": "RAM",
    "total_vehicles": 347,
    "keep": true
  },
  {
    "model": "CORONET",
    "total_vehicles": 117,
    "keep": true
  },
  {
    "model": "DART",
    "total_vehicles": 87,
    "keep": true
  },
  {
    "model": "AVENGER",
    "total_vehicles": 79,
    "keep": true
  },
  {
    "model": "VIPER",
    "total_vehicles": 74,
    "keep": true
  },
  {
    "model": "JC",
    "total_vehicles": 41,
    "keep": true
  },
  {
    "model": "POLARA",
    "total_vehicles": 33,
    "keep": true
  },
  {
    "model": "KINGSWAY",
    "total_vehicles": 21,
    "keep": true
  },
  {
    "model": "MONACO",
    "total_vehicles": 20,
    "keep": true
  },
  {
    "model": "TOURER",
    "total_vehicles": 19,
    "keep": true
  },
  {
    "model": "PIONEER",
    "total_vehicles": 19,
    "keep": true
  },
  {
    "model": "COUPE",
    "total_vehicles": 18,
    "keep": true
  },
  {
    "model": "4",
    "total_vehicles": 16,
    "keep": true
  },
  {
    "model": "DURANGO",
    "total_vehicles": 15,
    "keep": true
  },
  {
    "model": "DA",
    "total_vehicles": 14,
    "keep": true
  },
  {
    "model": "SUPER BEE",
    "total_vehicles": 11,
    "keep": true
  },
  {
    "model": "PHOENIX",
    "total_vehicles": 11,
    "keep": true
  },
  {
    "model": "D8",
    "total_vehicles": 9,
    "keep": true
  },
  {
    "model": "CUSTOM ROYAL",
    "total_vehicles": 9,
    "keep": true
  },
  {
    "model": "STANDARD 6",
    "total_vehicles": 8,
    "keep": true
  },
  {
    "model": "CUSTOM",
    "total_vehicles": 8,
    "keep": true
  },
  {
    "model": "VICTORY 6",
    "total_vehicles": 7,
    "keep": true
  },
  {
    "model": "SPECIAL",
    "total_vehicles": 7,
    "keep": true
  },
  {
    "model": "D5",
    "total_vehicles": 7,
    "keep": true
  },
  {
    "model": "ROADSTER",
    "total_vehicles": 6,
    "keep": true
  },
  {
    "model": "330",
    "total_vehicles": 6,
    "keep": true
  },
  {
    "model": "SENIOR",
    "total_vehicles": 5,
    "keep": true
  },
  {
    "model": "RAMCHARGER",
    "total_vehicles": 5,
    "keep": true
  },
  {
    "model": "DEMON",
    "total_vehicles": 5,
    "keep": true
  },
  {
    "model": "COMMAND",
    "total_vehicles": 5,
    "keep": true
  }
]